gmimtools/__init__.py
gmimtools/gmim.c
gmimtools/gmim.cp312-win_amd64.pyd
gmimtools/gmim.pyx
gmimtools/gmimtools.py
gmimtools-0.2.0.dist-info/LICENSE
gmimtools-0.2.0.dist-info/METADATA
gmimtools-0.2.0.dist-info/WHEEL
gmimtools-0.2.0.dist-info/top_level.txt
gmimtools-0.2.0.dist-info/RECORD
