Metadata-Version: 2.2
Name: gmimtools
Version: 0.2.0
Summary: A suite of ground motion intensity measure tools.
Home-page: https://github.com/RPretellD/gmimtools
Author: A. Renmin Pretell Ductram
Author-email: rpretell@unr.edu
License: MIT
Keywords: gmim
Classifier: Programming Language :: Python
Classifier: Programming Language :: Cython
Classifier: Programming Language :: Python :: 3
Classifier: License :: OSI Approved :: MIT License
Requires-Python: >=3.7
License-File: LICENSE
Requires-Dist: numpy
Requires-Dist: Cython
Dynamic: author
Dynamic: author-email
Dynamic: classifier
Dynamic: description
Dynamic: description-content-type
Dynamic: home-page
Dynamic: keywords
Dynamic: license
Dynamic: requires-dist
Dynamic: requires-python
Dynamic: summary
